nothing_pip-0.3.3.dist-info/METADATA
nothing_pip-0.3.3.dist-info/WHEEL
nothing_pip/__init__.py
nothing_pip/ping.py
nothing_pip-0.3.3.dist-info/RECORD
