Metadata-Version: 2.1
Name: nothing-pip
Version: 0.3.3
Summary: Let's share a program made with Python with mankind. It's nothing. It's easy.
Author-Email: dmario24 <data.mario24@gmail.com>
License: MIT
Project-URL: Homepage, https://github.com/edu-data-mario/nothing-pip
Project-URL: Bug tracker, https://github.com/edu-data-mario/nothing-pip/issues
Requires-Python: >=3.9
